{
  "schema_version": 1,
  "generated_at": "2026-07-07T22:36:09.917105+07:00",
  "summary": {
    "need_work": 6,
    "find_outbound": 6,
    "find_return": 0,
    "working": 20
  },
  "categories": [
    {
      "key": "find_outbound",
      "label": "หางานไป",
      "count": 6,
      "groups": [
        {
          "key": "dump",
          "label": "ดั้ม",
          "trucks": [
            {
              "number": "1290",
              "driver": "ยอด",
              "group": "dump",
              "category": "find_outbound",
              "gps_status": "รถจอด",
              "province": "ศรีสะเกษ",
              "district": "กันทรารมย์",
              "location_text": "ศรีสะเกษ · กันทรารมย์",
              "destination": "อุบลวัสดุ",
              "reason": "ขนกลับถึงบ้านแล้ว ว่างรับงานไป · 📍สินประดิษฐ์",
              "lat": 15.098712,
              "lon": 104.57435,
              "speed": 0,
              "heading": 90.0,
              "updated": "2026-07-07 22:35:38",
              "from_file": false,
              "stale": false,
              "at_station": "สินประดิษฐ์",
              "eta_hours": null,
              "fuel": null,
              "off_route": false
            },
            {
              "number": "2270",
              "driver": "รุ่ง",
              "group": "dump",
              "category": "find_outbound",
              "gps_status": "รถจอด",
              "province": "อุบลราชธานี",
              "district": "วารินชำราบ",
              "location_text": "อุบลราชธานี · วารินชำราบ",
              "destination": "ซีพีโนนคูณ",
              "reason": "ขนกลับถึงบ้านแล้ว ว่างรับงานไป",
              "lat": 15.077343,
              "lon": 104.9175,
              "speed": 0,
              "heading": 158.0,
              "updated": "2026-07-07 22:35:35",
              "from_file": false,
              "stale": false,
              "at_station": null,
              "eta_hours": null,
              "fuel": null,
              "off_route": false
            }
          ]
        },
        {
          "key": "flatbed",
          "label": "พื้นเรียบ",
          "trucks": [
            {
              "number": "1300",
              "driver": "เอ็ม2",
              "group": "flatbed",
              "category": "find_outbound",
              "gps_status": "รถจอด",
              "province": "ศรีสะเกษ",
              "district": "กันทรารมย์",
              "location_text": "ศรีสะเกษ · กันทรารมย์",
              "destination": "พิบูล",
              "reason": "ขนกลับถึงบ้านแล้ว ว่างรับงานไป · 📍สินประดิษฐ์",
              "lat": 15.098433,
              "lon": 104.57466,
              "speed": 0,
              "heading": 90.0,
              "updated": "2026-07-07 22:31:11",
              "from_file": false,
              "stale": false,
              "at_station": "สินประดิษฐ์",
              "eta_hours": null,
              "fuel": null,
              "off_route": false
            },
            {
              "number": "3001",
              "driver": "จำนง",
              "group": "flatbed",
              "category": "find_outbound",
              "gps_status": "รถจอด",
              "province": "ศรีสะเกษ",
              "district": "กันทรารมย์",
              "location_text": "ศรีสะเกษ · กันทรารมย์",
              "destination": "ศิริมหาชัย ศก",
              "reason": "ขนกลับถึงบ้านแล้ว ว่างรับงานไป · 📍สินประดิษฐ์",
              "lat": 15.098318,
              "lon": 104.57442,
              "speed": 0,
              "heading": 0.0,
              "updated": "2026-07-07 22:33:14",
              "from_file": false,
              "stale": false,
              "at_station": "สินประดิษฐ์",
              "eta_hours": null,
              "fuel": null,
              "off_route": false
            },
            {
              "number": "3070",
              "driver": "เอ็ม",
              "group": "flatbed",
              "category": "find_outbound",
              "gps_status": "รถจอด",
              "province": "ศรีสะเกษ",
              "district": "กันทรารมย์",
              "location_text": "ศรีสะเกษ · กันทรารมย์",
              "destination": "ส.กันทรลักษ์",
              "reason": "ขนกลับถึงบ้านแล้ว ว่างรับงานไป · 📍สินประดิษฐ์",
              "lat": 15.099024,
              "lon": 104.57502,
              "speed": 0,
              "heading": 23.0,
              "updated": "2026-07-07 22:31:42",
              "from_file": false,
              "stale": false,
              "at_station": "สินประดิษฐ์",
              "eta_hours": null,
              "fuel": null,
              "off_route": false
            },
            {
              "number": "3971",
              "driver": "แม็กซ์",
              "group": "flatbed",
              "category": "find_outbound",
              "gps_status": "รถจอด",
              "province": "ศรีสะเกษ",
              "district": "กันทรารมย์",
              "location_text": "ศรีสะเกษ · กันทรารมย์",
              "destination": "เมืองวัสดุ",
              "reason": "ขนกลับถึงบ้านแล้ว ว่างรับงานไป · 📍สินประดิษฐ์",
              "lat": 15.098397,
              "lon": 104.574867,
              "speed": 0,
              "heading": 0.0,
              "updated": "2026-07-07 22:32:51",
              "from_file": false,
              "stale": false,
              "at_station": "สินประดิษฐ์",
              "eta_hours": null,
              "fuel": null,
              "off_route": false
            }
          ]
        }
      ]
    },
    {
      "key": "find_return",
      "label": "หางานกลับ",
      "count": 0,
      "groups": []
    },
    {
      "key": "working",
      "label": "อยู่ระหว่างทำงาน",
      "count": 20,
      "groups": [
        {
          "key": "dump",
          "label": "ดั้ม",
          "trucks": [
            {
              "number": "1571",
              "driver": "ตั้ม",
              "group": "dump",
              "category": "working",
              "gps_status": "รถจอด",
              "province": "นครราชสีมา",
              "district": "สูงเนิน",
              "location_text": "นครราชสีมา · สูงเนิน",
              "destination": "กระชับมิตร",
              "reason": "กำลังไปส่ง — ถึง นครราชสีมา แล้ว ยังไม่ถึง กระชับมิตร · อีก ~2 ชม. ถึง กระชับมิตร",
              "lat": 14.85036,
              "lon": 101.71868,
              "speed": 0,
              "heading": 270.0,
              "updated": "2026-07-07 22:35:05",
              "from_file": false,
              "stale": false,
              "at_station": null,
              "eta_hours": 2.0,
              "fuel": null,
              "off_route": false
            },
            {
              "number": "2943",
              "driver": "ต้อม",
              "group": "dump",
              "category": "working",
              "gps_status": "รถจอด",
              "province": "ปทุมธานี",
              "district": "ลำลูกกา",
              "location_text": "ปทุมธานี · ลำลูกกา",
              "destination": "อุบลวัสดุ",
              "reason": "กำลังขนกลับ · อีก ~8 ชม. ถึงบ้าน · 📍ศูนย์กระจายสินค้าดูโฮม ลำลูกกา",
              "lat": 13.986653,
              "lon": 100.74891,
              "speed": 0,
              "heading": 203.0,
              "updated": "2026-07-07 22:33:48",
              "from_file": false,
              "stale": false,
              "at_station": "ศูนย์กระจายสินค้าดูโฮม ลำลูกกา",
              "eta_hours": 8.2,
              "fuel": null,
              "off_route": false
            }
          ]
        },
        {
          "key": "pen",
          "label": "คอก",
          "trucks": [
            {
              "number": "1266",
              "driver": "เพชร",
              "group": "pen",
              "category": "working",
              "gps_status": "รถจอด",
              "province": "นครราชสีมา",
              "district": "สีคิ้ว",
              "location_text": "นครราชสีมา · สีคิ้ว",
              "destination": "ไทยฟ้า",
              "reason": "กำลังไปส่ง — ถึง นครราชสีมา แล้ว ยังไม่ถึง ไทยฟ้า",
              "lat": 14.856075,
              "lon": 101.70224,
              "speed": 0,
              "heading": 68.0,
              "updated": "2026-07-07 22:35:20",
              "from_file": false,
              "stale": false,
              "at_station": null,
              "eta_hours": null,
              "fuel": null,
              "off_route": false
            },
            {
              "number": "1268",
              "driver": "สิน",
              "group": "pen",
              "category": "working",
              "gps_status": "รถจอด",
              "province": "ฉะเชิงเทรา",
              "district": "บางปะกง",
              "location_text": "ฉะเชิงเทรา · บางปะกง",
              "destination": "ซีพีศรีสะเกษ",
              "reason": "กำลังขนกลับ · อีก ~8 ชม. ถึงบ้าน",
              "lat": 13.505923,
              "lon": 100.9813,
              "speed": 0,
              "heading": 0.0,
              "updated": "2026-07-07 22:34:19",
              "from_file": false,
              "stale": false,
              "at_station": null,
              "eta_hours": 8.2,
              "fuel": null,
              "off_route": false
            },
            {
              "number": "1286",
              "driver": "เดวิด",
              "group": "pen",
              "category": "working",
              "gps_status": "รถวิ่ง",
              "province": "นครราชสีมา",
              "district": "ปากช่อง",
              "location_text": "นครราชสีมา · ปากช่อง",
              "destination": "นครหลวง",
              "reason": "กำลังไปส่ง — ถึง นครราชสีมา แล้ว ยังไม่ถึง นครหลวง · อีก ~1.5 ชม. ถึง ซีพี นครหลวง",
              "lat": 14.654676,
              "lon": 101.36576,
              "speed": 19,
              "heading": 203.0,
              "updated": "2026-07-07 22:35:53",
              "from_file": false,
              "stale": false,
              "at_station": null,
              "eta_hours": 1.7,
              "fuel": null,
              "off_route": false
            }
          ]
        },
        {
          "key": "flatbed",
          "label": "พื้นเรียบ",
          "trucks": [
            {
              "number": "1163",
              "driver": "ต่อ",
              "group": "flatbed",
              "category": "working",
              "gps_status": "รถจอด",
              "province": "นนทบุรี",
              "district": null,
              "location_text": "นนทบุรี",
              "destination": "เมืองวัสดุ",
              "reason": "อยู่ที่ เจียเม้ง นนทบุรี — ส่งของ (มีงานกลับต่อ) · GPS เจ้าที่ 2",
              "lat": 13.862833333333,
              "lon": 100.48188333333,
              "speed": 0,
              "heading": 0.0,
              "updated": "2026-07-07 22:28:49",
              "from_file": false,
              "stale": false,
              "at_station": "เจียเม้ง นนทบุรี",
              "eta_hours": null,
              "fuel": 33,
              "off_route": false
            },
            {
              "number": "1169",
              "driver": "ศักดิ์",
              "group": "flatbed",
              "category": "working",
              "gps_status": "รถจอด",
              "province": "ปราจีนบุรี",
              "district": "บ้านสร้าง",
              "location_text": "ปราจีนบุรี · บ้านสร้าง",
              "destination": "เมืองวัสดุ",
              "reason": "กำลังขนกลับ · อีก ~8 ชม. ถึงบ้าน",
              "lat": 13.984852,
              "lon": 101.222015,
              "speed": 0,
              "heading": 0.0,
              "updated": "2026-07-07 22:32:05",
              "from_file": false,
              "stale": false,
              "at_station": null,
              "eta_hours": 7.9,
              "fuel": null,
              "off_route": false
            },
            {
              "number": "1974",
              "driver": "พัน",
              "group": "flatbed",
              "category": "working",
              "gps_status": "รถวิ่ง",
              "province": "สุรินทร์",
              "district": "เมืองสุรินทร์",
              "location_text": "สุรินทร์ · เมืองสุรินทร์",
              "destination": "นนทบุรี",
              "reason": "รับงานขาไปแล้ว กำลังจะออก",
              "lat": 14.796197,
              "lon": 103.44978,
              "speed": 58,
              "heading": 248.0,
              "updated": "2026-07-07 22:36:05",
              "from_file": false,
              "stale": false,
              "at_station": null,
              "eta_hours": null,
              "fuel": null,
              "off_route": false
            },
            {
              "number": "2187",
              "driver": "ป้อม",
              "group": "flatbed",
              "category": "working",
              "gps_status": "รถจอด",
              "province": "สระบุรี",
              "district": "หนองแค",
              "location_text": "สระบุรี · หนองแค",
              "destination": "ศิริมหาชัย อบ",
              "reason": "กำลังขนกลับ · อีก ~7.5 ชม. ถึงบ้าน",
              "lat": 14.334811,
              "lon": 100.85142,
              "speed": 0,
              "heading": 0.0,
              "updated": "2026-07-07 22:31:32",
              "from_file": false,
              "stale": false,
              "at_station": null,
              "eta_hours": 7.4,
              "fuel": null,
              "off_route": false
            },
            {
              "number": "2592",
              "driver": "บิน",
              "group": "flatbed",
              "category": "working",
              "gps_status": "รถจอด",
              "province": "นครราชสีมา",
              "district": "ปากช่อง",
              "location_text": "นครราชสีมา · ปากช่อง",
              "destination": "ศิริมหาชัย ศก",
              "reason": "กำลังไปส่ง (กระชับมิตร) · อีก ~1.5 ชม. ถึง กระชับมิตร",
              "lat": 14.733079,
              "lon": 101.506905,
              "speed": 0,
              "heading": 315.0,
              "updated": "2026-07-07 22:33:34",
              "from_file": false,
              "stale": false,
              "at_station": null,
              "eta_hours": 1.6,
              "fuel": null,
              "off_route": false
            },
            {
              "number": "2792",
              "driver": "หมู",
              "group": "flatbed",
              "category": "working",
              "gps_status": "จอดไม่ดับเครื่อง",
              "province": "นครราชสีมา",
              "district": "สูงเนิน",
              "location_text": "นครราชสีมา · สูงเนิน",
              "destination": "ศิริมหาชัย ศก",
              "reason": "กำลังไปส่ง (แหลมฉบัง) · อีก ~4.5 ชม. ถึง โกดังแหลมฉบัง",
              "lat": 14.84268,
              "lon": 101.75191,
              "speed": 0,
              "heading": 270.0,
              "updated": "2026-07-07 22:34:46",
              "from_file": false,
              "stale": false,
              "at_station": null,
              "eta_hours": 4.6,
              "fuel": null,
              "off_route": false
            },
            {
              "number": "2827",
              "driver": "เอ็ม2",
              "group": "flatbed",
              "category": "working",
              "gps_status": "รถวิ่ง",
              "province": "สุรินทร์",
              "district": "ปราสาท",
              "location_text": "สุรินทร์ · ปราสาท",
              "destination": "นนทบุรี",
              "reason": "รับงานขาไปแล้ว กำลังจะออก",
              "lat": 14.631425,
              "lon": 103.41192,
              "speed": 49,
              "heading": 203.0,
              "updated": "2026-07-07 22:35:19",
              "from_file": false,
              "stale": false,
              "at_station": null,
              "eta_hours": null,
              "fuel": null,
              "off_route": false
            },
            {
              "number": "3066",
              "driver": "คอม",
              "group": "flatbed",
              "category": "working",
              "gps_status": "รถวิ่ง",
              "province": "ปทุมธานี",
              "district": "ลาดหลุมแก้ว",
              "location_text": "ปทุมธานี · ลาดหลุมแก้ว",
              "destination": "เมืองวัสดุ",
              "reason": "กำลังไปส่ง (นนทบุรี) · อีก ~30 นาที ถึง เจียเม้ง นนทบุรี",
              "lat": 14.033541,
              "lon": 100.45216,
              "speed": 46,
              "heading": 248.0,
              "updated": "2026-07-07 22:35:44",
              "from_file": false,
              "stale": false,
              "at_station": null,
              "eta_hours": 0.6,
              "fuel": null,
              "off_route": false
            },
            {
              "number": "3604",
              "driver": "บี",
              "group": "flatbed",
              "category": "working",
              "gps_status": "รถวิ่ง",
              "province": "สุรินทร์",
              "district": "ปราสาท",
              "location_text": "สุรินทร์ · ปราสาท",
              "destination": "กระชับมิตร",
              "reason": "รับงานขาไปแล้ว กำลังจะออก",
              "lat": 14.627657,
              "lon": 103.25074,
              "speed": 0,
              "heading": 23.0,
              "updated": "2026-07-07 22:35:54",
              "from_file": false,
              "stale": false,
              "at_station": null,
              "eta_hours": null,
              "fuel": null,
              "off_route": false
            },
            {
              "number": "3606",
              "driver": "สุพจ",
              "group": "flatbed",
              "category": "working",
              "gps_status": "รถวิ่ง",
              "province": "บุรีรัมย์",
              "district": "ประโคนชัย",
              "location_text": "บุรีรัมย์ · ประโคนชัย",
              "destination": "เมืองวัสดุ",
              "reason": "กำลังไปส่ง (สุพรรณบุรี)",
              "lat": 14.630851,
              "lon": 103.239555,
              "speed": 56,
              "heading": 338.0,
              "updated": "2026-07-07 22:36:11",
              "from_file": false,
              "stale": false,
              "at_station": null,
              "eta_hours": null,
              "fuel": null,
              "off_route": false
            },
            {
              "number": "3608",
              "driver": "อำนาจ",
              "group": "flatbed",
              "category": "working",
              "gps_status": "รถจอด",
              "province": "นครราชสีมา",
              "district": "สูงเนิน",
              "location_text": "นครราชสีมา · สูงเนิน",
              "destination": "สุพรรณบุรี",
              "reason": "กำลังไปส่ง — ถึง นครราชสีมา แล้ว ยังไม่ถึง สุพรรณบุรี",
              "lat": 14.83346,
              "lon": 101.781952,
              "speed": 0,
              "heading": 113.0,
              "updated": "2026-07-07 22:34:41",
              "from_file": false,
              "stale": false,
              "at_station": null,
              "eta_hours": null,
              "fuel": null,
              "off_route": false
            },
            {
              "number": "3610",
              "driver": "บรรณ",
              "group": "flatbed",
              "category": "working",
              "gps_status": "จอดไม่ดับเครื่อง",
              "province": "นนทบุรี",
              "district": "เมืองนนทบุรี",
              "location_text": "นนทบุรี · เมืองนนทบุรี",
              "destination": "เมืองวัสดุ",
              "reason": "อยู่ที่ เจียเม้ง นนทบุรี — ส่งของ (มีงานกลับต่อ)",
              "lat": 13.862555,
              "lon": 100.48204,
              "speed": 0,
              "heading": 203.0,
              "updated": "2026-07-07 22:33:24",
              "from_file": false,
              "stale": false,
              "at_station": "เจียเม้ง นนทบุรี",
              "eta_hours": null,
              "fuel": null,
              "off_route": false
            },
            {
              "number": "3637",
              "driver": "สอ",
              "group": "flatbed",
              "category": "working",
              "gps_status": "รถจอด",
              "province": "ศรีสะเกษ",
              "district": "เมืองศรีสะเกษ",
              "location_text": "ศรีสะเกษ · เมืองศรีสะเกษ",
              "destination": "นนทบุรี",
              "reason": "รับงานขาไปแล้ว กำลังจะออก · 📍เจียเม้ง ศรีสะเกษ",
              "lat": 15.074026,
              "lon": 104.344315,
              "speed": 0,
              "heading": 0.0,
              "updated": "2026-07-07 22:31:49",
              "from_file": false,
              "stale": false,
              "at_station": "เจียเม้ง ศรีสะเกษ",
              "eta_hours": null,
              "fuel": null,
              "off_route": false
            },
            {
              "number": "4100",
              "driver": "เล่",
              "group": "flatbed",
              "category": "working",
              "gps_status": "รถจอด",
              "province": "ศรีสะเกษ",
              "district": null,
              "location_text": "ศรีสะเกษ",
              "destination": "นนทบุรี",
              "reason": "รับงานขาไปแล้ว กำลังจะออก · 📍เจียเม้ง ศรีสะเกษ · GPS เจ้าที่ 2",
              "lat": 15.074216666667,
              "lon": 104.34468333333,
              "speed": 0,
              "heading": 0.0,
              "updated": "2026-07-07 22:28:34",
              "from_file": false,
              "stale": false,
              "at_station": "เจียเม้ง ศรีสะเกษ",
              "eta_hours": null,
              "fuel": 100,
              "off_route": false
            },
            {
              "number": "4102",
              "driver": "เอ็ม",
              "group": "flatbed",
              "category": "working",
              "gps_status": "รถจอด",
              "province": "ศรีสะเกษ",
              "district": null,
              "location_text": "ศรีสะเกษ",
              "destination": "นนทบุรี",
              "reason": "รับงานขาไปแล้ว กำลังจะออก · 📍เจียเม้ง ศรีสะเกษ · GPS เจ้าที่ 2",
              "lat": 15.0739,
              "lon": 104.3447,
              "speed": 0,
              "heading": 0.0,
              "updated": "2026-07-07 22:27:33",
              "from_file": false,
              "stale": false,
              "at_station": "เจียเม้ง ศรีสะเกษ",
              "eta_hours": null,
              "fuel": 100,
              "off_route": false
            }
          ]
        }
      ]
    }
  ]
}